tree_rank/__init__.py
tree_rank/__main__.py
tree_rank/core.py
tree_rank-0.1.0.dist-info/licenses/LICENSE
tree_rank-0.1.0.dist-info/METADATA
tree_rank-0.1.0.dist-info/WHEEL
tree_rank-0.1.0.dist-info/entry_points.txt
tree_rank-0.1.0.dist-info/top_level.txt
tree_rank-0.1.0.dist-info/RECORD
