Metadata-Version: 2.4
Name: tree-rank
Version: 0.1.0
Summary: Prints a clean directory structure, ignoring unnecessary folders across tech stacks
Author-email: Sushruth Samson <samsushruth@gmail.com>
License-Expression: MIT
Requires-Python: >=3.7
License-File: LICENSE
Dynamic: license-file
